{"container_type": "Author", "filled": ["basics", "publications", "indices", "counts"], "scholar_id": "mQFL3DYAAAAJ", "source": "AUTHOR_PROFILE_PAGE", "name": "Tang Li", "url_picture": "https://scholar.googleusercontent.com/citations?view_op=view_photo&user=mQFL3DYAAAAJ&citpid=4", "affiliation": "Ph.D. student, University of Delaware", "organization": 9340941294191691364, "interests": ["Explainable AI", "Machine Learning", "Computer Vision", "Scientific Machine Learning"], "email_domain": "@udel.edu", "homepage": "https://tangli0305.github.io/", "citedby": 33, "publications": {"mQFL3DYAAAAJ:qjMakFHDy7sC": {"container_type": "Publication", "source": "AUTHOR_PUBLICATION_ENTRY", "bib": {"title": "Are Data-driven Explanations Robust against Out-of-distribution Data?", "pub_year": "2023"}, "filled": false, "author_pub_id": "mQFL3DYAAAAJ:qjMakFHDy7sC", "num_citations": 12, "citedby_url": "https://scholar.google.com/scholar?oi=bibs&hl=en&cites=10814077390749896301", "cites_id": ["10814077390749896301"]}, "mQFL3DYAAAAJ:u5HHmVD_uO8C": {"container_type": "Publication", "source": "AUTHOR_PUBLICATION_ENTRY", "bib": {"title": "Deep Learning for Spatiotemporal Modeling of Urbanization", "pub_year": "2021"}, "filled": false, "author_pub_id": "mQFL3DYAAAAJ:u5HHmVD_uO8C", "num_citations": 10, "citedby_url": "https://scholar.google.com/scholar?oi=bibs&hl=en&cites=18336143267360646729", "cites_id": ["18336143267360646729"]}, "mQFL3DYAAAAJ:UeHWp8X0CEIC": {"container_type": "Publication", "source": "AUTHOR_PUBLICATION_ENTRY", "bib": {"title": "Beyond the Federation: Topology-aware Federated Learning for Generalization to Unseen Clients", "pub_year": "2024"}, "filled": false, "author_pub_id": "mQFL3DYAAAAJ:UeHWp8X0CEIC", "num_citations": 6, "citedby_url": "https://scholar.google.com/scholar?oi=bibs&hl=en&cites=11553916373948922544", "cites_id": ["11553916373948922544"]}, "mQFL3DYAAAAJ:_FxGoFyzp5QC": {"container_type": "Publication", "source": "AUTHOR_PUBLICATION_ENTRY", "bib": {"title": "Deal: Disentangle and localize concept-level explanations for vlms", "pub_year": "2025"}, "filled": false, "author_pub_id": "mQFL3DYAAAAJ:_FxGoFyzp5QC", "num_citations": 4, "citedby_url": "https://scholar.google.com/scholar?oi=bibs&hl=en&cites=14272495875302725156", "cites_id": ["14272495875302725156"]}, "mQFL3DYAAAAJ:YsMSGLbcyi4C": {"container_type": "Publication", "source": "AUTHOR_PUBLICATION_ENTRY", "bib": {"title": "Beyond Accuracy: Ensuring Correct Predictions With Correct Rationales", "pub_year": "2024"}, "filled": false, "author_pub_id": "mQFL3DYAAAAJ:YsMSGLbcyi4C", "num_citations": 1, "citedby_url": "https://scholar.google.com/scholar?oi=bibs&hl=en&cites=7180162550889207599", "cites_id": ["7180162550889207599"]}, "mQFL3DYAAAAJ:LkGwnXOMwfcC": {"container_type": "Publication", "source": "AUTHOR_PUBLICATION_ENTRY", "bib": {"title": "Beyond Accuracy: On the Effects of Fine-tuning Towards Vision-Language Model's Prediction Rationality", "pub_year": "2024"}, "filled": false, "author_pub_id": "mQFL3DYAAAAJ:LkGwnXOMwfcC", "num_citations": 0}}, "citedby5y": 33, "hindex": 4, "hindex5y": 4, "i10index": 2, "i10index5y": 2, "cites_per_year": {"2023": 8, "2024": 23, "2025": 2}, "updated": "2025-02-10 08:16:25.523067"}